panaetius/__init__.py
panaetius/_version.py
panaetius/config.py
panaetius/exceptions.py
panaetius/library.py
panaetius/logging.py
panaetius/py.typed
panaetius/utilities/__init__.py
panaetius/utilities/squasher.py
panaetius-2.3.5.dist-info/LICENSE
panaetius-2.3.5.dist-info/WHEEL
panaetius-2.3.5.dist-info/METADATA
panaetius-2.3.5.dist-info/RECORD
