Metadata-Version: 2.1
Name: panaetius
Version: 2.3.5
Summary: Python module to gracefully handle a .config file/environment variables for scripts, with built in masking for sensitive options. Provides a Splunk friendly formatted logger instance.
Home-page: https://github.com/dtomlinson91/panaetius
License: MIT
Author: dtomlinson
Author-email: dtomlinson@panaetius.co.uk
Requires-Python: >=3.7,<4.0
Classifier: Environment :: MacOS X
Classifier: Environment :: Plugins
Classifier: Intended Audience :: Developers
Classifier: License :: OSI Approved :: MIT License
Classifier: Natural Language :: English
Classifier: Operating System :: POSIX :: Linux
Classifier: Programming Language :: Python :: 3
Classifier: Programming Language :: Python :: 3 :: Only
Classifier: Programming Language :: Python :: 3.10
Classifier: Programming Language :: Python :: 3.7
Classifier: Programming Language :: Python :: 3.8
Classifier: Programming Language :: Python :: 3.9
Classifier: Topic :: Software Development
Classifier: Topic :: Software Development :: Libraries
Classifier: Topic :: Utilities
Requires-Dist: PyYAML
Project-URL: Documentation, https://panaetius.readthedocs.io/en/latest/introduction.html
Project-URL: Repository, https://github.com/dtomlinson91/panaetius
